whisper/__init__.py
whisper/__main__.py
whisper/audio.py
whisper/decoding.py
whisper/model.py
whisper/tokenizer.py
whisper/transcribe.py
whisper/utils.py
whisper/assets/mel_filters.npz
whisper/assets/gpt2/merges.txt
whisper/assets/gpt2/special_tokens_map.json
whisper/assets/gpt2/tokenizer_config.json
whisper/assets/gpt2/vocab.json
whisper/assets/multilingual/added_tokens.json
whisper/assets/multilingual/merges.txt
whisper/assets/multilingual/special_tokens_map.json
whisper/assets/multilingual/tokenizer_config.json
whisper/assets/multilingual/vocab.json
whisper/normalizers/__init__.py
whisper/normalizers/basic.py
whisper/normalizers/english.json
whisper/normalizers/english.py
whisper_openai-1.0.0.dist-info/LICENSE
whisper_openai-1.0.0.dist-info/METADATA
whisper_openai-1.0.0.dist-info/WHEEL
whisper_openai-1.0.0.dist-info/entry_points.txt
whisper_openai-1.0.0.dist-info/top_level.txt
whisper_openai-1.0.0.dist-info/RECORD
