Metadata-Version: 2.1
Name: whisper-openai
Version: 1.0.0
Summary: Robust Speech Recognition via Large-Scale Weak Supervision
Home-page: https://github.com/openai/whisper
Author: OpenAI
License: MIT
Platform: UNKNOWN
Requires-Python: >=3.7
Provides-Extra: dev
